{
  "_class": "group",
  "booleanOperation": 0,
  "clippingMaskMode": 0,
  "do_objectID": "9BB13E1D-44E7-4AC3-9D9B-4CEAD257D2F0",
  "exportOptions": {
    "_class": "exportOptions",
    "exportFormats": [
    ],
    "includedLayerIds": [
    ],
    "layerOptions": 0,
    "shouldTrim": false
  },
  "flow": {
    "_class": "MSImmutableFlowConnection",
    "animationType": -1,
    "destinationArtboardID": "4895DDB7-9AF3-40B5-9F97-DE2E5DAEDAD6"
  },
  "frame": {
    "_class": "rect",
    "constrainProportions": false,
    "height": 170,
    "width": 646,
    "x": 275,
    "y": 25
  },
  "groupLayout": {
    "_class": "MSImmutableFreeformGroupLayout"
  },
  "hasClickThrough": false,
  "hasClippingMask": false,
  "isFixedToViewport": false,
  "isFlippedHorizontal": false,
  "isFlippedVertical": false,
  "isLocked": false,
  "isVisible": true,
  "layerListExpandedType": 0,
  "layers": [
    {
      "class": "rectangle",
      "id": "04899831-0188-48A1-A65A-ABFBD0F843A5"
    },
    {
      "class": "group",
      "id": "C166EE1F-3A7B-40FE-8155-DDD11CCFB75B"
    },
    {
      "class": "symbolInstance",
      "id": "B1D71DB1-A015-4FE0-B695-E3A6080417AB"
    }
  ],
  "name": "Assignment",
  "nameIsFixed": true,
  "resizingConstraint": 63,
  "resizingType": 0,
  "rotation": 0,
  "shouldBreakMaskChain": false,
  "style": {
    "_class": "style",
    "endMarkerType": 0,
    "miterLimit": 10,
    "startMarkerType": 0,
    "windingRule": 1
  }
}