{
  "_class": "symbolInstance",
  "booleanOperation": 0,
  "clippingMaskMode": 0,
  "do_objectID": "45AD1CE0-E103-49A2-BBEB-F31D61367729",
  "exportOptions": {
    "_class": "exportOptions",
    "do_objectID": "E660D568-AA1E-4C4A-8BC7-2707788E54C9",
    "exportFormats": [
    ],
    "includedLayerIds": [
    ],
    "layerOptions": 0,
    "shouldTrim": false
  },
  "frame": {
    "_class": "rect",
    "constrainProportions": false,
    "do_objectID": "C3033FA3-ADA7-4407-9977-22A77C7BC484",
    "height": 35,
    "width": 325,
    "x": 0,
    "y": 349
  },
  "hasClippingMask": false,
  "horizontalSpacing": 0,
  "isFixedToViewport": false,
  "isFlippedHorizontal": false,
  "isFlippedVertical": false,
  "isLocked": false,
  "isVisible": true,
  "layerListExpandedType": 0,
  "name": "Test case",
  "nameIsFixed": true,
  "overrideValues": [
    {
      "_class": "overrideValue",
      "overrideName": "D516F933-432A-4870-B657-BC7548FE7F0E_stringValue",
      "value": "main(\"another\", \"test\") -> \"another test\""
    },
    {
      "_class": "overrideValue",
      "do_objectID": "C5E9C9B4-FEAA-4628-84EA-39345F8FCCDD",
      "overrideName": "C802D596-6DB9-4EA8-A87E-72250C47EAC4_symbolID",
      "value": "E016CB8A-7E33-4FFD-AF7C-63A9137CF76F"
    }
  ],
  "resizingConstraint": 63,
  "resizingType": 0,
  "rotation": 0,
  "scale": 1,
  "shouldBreakMaskChain": false,
  "style": {
    "_class": "style",
    "do_objectID": "21332EE6-5126-497A-BA1B-52278EAB7226",
    "endMarkerType": 0,
    "miterLimit": 10,
    "startMarkerType": 0,
    "windingRule": 1
  },
  "symbolID": "6083A37F-F9BB-40BF-932C-F9BA31A18997",
  "verticalSpacing": 0
}