{
  "_class": "group",
  "booleanOperation": -1,
  "clippingMaskMode": 0,
  "do_objectID": "AC04E793-3924-47FD-9DCA-16FB8DA01E2B",
  "exportOptions": {
    "_class": "exportOptions",
    "do_objectID": "DE1B79B0-90F6-4FC6-B5F3-D64073641061",
    "exportFormats": [
    ],
    "includedLayerIds": [
    ],
    "layerOptions": 0,
    "shouldTrim": false
  },
  "frame": {
    "_class": "rect",
    "constrainProportions": false,
    "do_objectID": "369F0E4C-FA1B-4D77-81A0-05C2E7FFCAC8",
    "height": 27,
    "width": 307.5409836065574,
    "x": 195,
    "y": 10
  },
  "groupLayout": {
    "_class": "MSImmutableFreeformGroupLayout",
    "do_objectID": "B4910340-B752-4742-9912-79A89472773A"
  },
  "hasClickThrough": false,
  "hasClippingMask": false,
  "isFixedToViewport": false,
  "isFlippedHorizontal": false,
  "isFlippedVertical": false,
  "isLocked": false,
  "isVisible": true,
  "layerListExpandedType": 0,
  "layers": [
    {
      "class": "group",
      "id": "96542276-8A13-4F01-8FAF-C848413EF278"
    },
    {
      "class": "rectangle",
      "id": "0EBA6D90-0983-464C-9A74-C08BAB2AAB5A"
    },
    {
      "class": "rectangle",
      "id": "52B0181B-3DC5-447D-94C5-4F8C31EA6C3B"
    }
  ],
  "name": "Correct balance",
  "nameIsFixed": true,
  "resizingConstraint": 63,
  "resizingType": 0,
  "rotation": 0,
  "shouldBreakMaskChain": false,
  "style": {
    "_class": "style",
    "do_objectID": "50F42368-D5AD-417B-8B98-042F919BEFFD",
    "endMarkerType": 0,
    "miterLimit": 10,
    "startMarkerType": 0,
    "windingRule": 1
  }
}