{
  "_class": "symbolInstance",
  "booleanOperation": 0,
  "clippingMaskMode": 0,
  "do_objectID": "1475BECC-0BA8-4984-BE7C-ED8EBE27D646",
  "exportOptions": {
    "_class": "exportOptions",
    "exportFormats": [
    ],
    "includedLayerIds": [
    ],
    "layerOptions": 0,
    "shouldTrim": false
  },
  "frame": {
    "_class": "rect",
    "constrainProportions": true,
    "height": 14,
    "width": 14,
    "x": 0,
    "y": 0
  },
  "hasClippingMask": false,
  "horizontalSpacing": 0,
  "isFixedToViewport": false,
  "isFlippedHorizontal": false,
  "isFlippedVertical": false,
  "isLocked": false,
  "isVisible": true,
  "layerListExpandedType": 0,
  "name": "icon / chevron",
  "nameIsFixed": true,
  "overrideValues": [
    {
      "_class": "overrideValue",
      "do_objectID": "854EDF78-CB98-487D-BDCD-EE77335B874A",
      "overrideName": "00167D8B-5B08-4128-B928-DBD251060616_symbolID",
      "value": "9A9DA484-1D6B-4848-B8F5-118A64D24712"
    },
    {
      "_class": "overrideValue",
      "do_objectID": "2770D274-7218-4E33-8B22-F3F5B556D18C",
      "overrideName": "0A95E32B-51A8-4D74-8871-21F53181EE47_symbolID",
      "value": "2651116C-CA75-4D0D-814B-BA2463036101"
    }
  ],
  "resizingConstraint": 41,
  "resizingType": 0,
  "rotation": 0,
  "scale": 1,
  "shouldBreakMaskChain": false,
  "style": {
    "_class": "style",
    "endMarkerType": 0,
    "miterLimit": 10,
    "startMarkerType": 0,
    "windingRule": 1
  },
  "symbolID": "7A4E9E01-D0ED-4526-A8F8-BC2D43115936",
  "verticalSpacing": 0
}