{
  "_class": "group",
  "booleanOperation": -1,
  "clippingMaskMode": 0,
  "do_objectID": "C030F14B-872C-48C5-97BD-C56DA50438F6",
  "exportOptions": {
    "_class": "exportOptions",
    "do_objectID": "B2B81093-444F-4ADD-9CA3-7FDBF4CB9647",
    "exportFormats": [
    ],
    "includedLayerIds": [
    ],
    "layerOptions": 0,
    "shouldTrim": false
  },
  "frame": {
    "_class": "rect",
    "constrainProportions": false,
    "do_objectID": "9D3C0108-C805-4330-8B2A-B49AC0F86FE5",
    "height": 139,
    "width": 442,
    "x": 0,
    "y": 0
  },
  "groupLayout": {
    "_class": "MSImmutableFreeformGroupLayout",
    "do_objectID": "C79E47DE-791A-4AEB-8AFC-058828BB11A6"
  },
  "hasClickThrough": false,
  "hasClippingMask": false,
  "isFixedToViewport": false,
  "isFlippedHorizontal": false,
  "isFlippedVertical": false,
  "isLocked": false,
  "isVisible": true,
  "layerListExpandedType": 2,
  "layers": [
    {
      "class": "text",
      "id": "913D6C95-0185-4EC6-8A85-86E4706551C6"
    },
    {
      "class": "text",
      "id": "DFC1C0FD-D6B8-4AA7-B924-674B88255BAA"
    },
    {
      "class": "text",
      "id": "CFC11D11-23CD-4C6F-864C-8EA862F0CB7A"
    },
    {
      "class": "text",
      "id": "8D4BEE42-8DE8-426C-985B-58BAF291746D"
    }
  ],
  "name": "Group",
  "nameIsFixed": false,
  "resizingConstraint": 11,
  "resizingType": 0,
  "rotation": 0,
  "shouldBreakMaskChain": false,
  "style": {
    "_class": "style",
    "do_objectID": "0289C4A3-0B1F-416E-97E6-D15D9BC3AAFF",
    "endMarkerType": 0,
    "miterLimit": 10,
    "startMarkerType": 0,
    "windingRule": 1
  }
}