{
  "_class": "symbolMaster",
  "allowsOverrides": true,
  "backgroundColor": {
    "_class": "color",
    "alpha": 1,
    "blue": 0.1294117647058823,
    "green": 0.1176470588235294,
    "red": 0.1176470588235294
  },
  "booleanOperation": -1,
  "changeIdentifier": 2464,
  "clippingMaskMode": 0,
  "do_objectID": "15C143A3-5852-4C40-8777-F2E072EC27BC",
  "exportOptions": {
    "_class": "exportOptions",
    "exportFormats": [
      {
        "_class": "exportFormat",
        "absoluteSize": 0,
        "fileFormat": "svg",
        "name": "",
        "namingScheme": 0,
        "scale": 1,
        "visibleScaleType": 0
      }
    ],
    "includedLayerIds": [
    ],
    "layerOptions": 0,
    "shouldTrim": false
  },
  "frame": {
    "_class": "rect",
    "constrainProportions": false,
    "height": 222,
    "width": 172,
    "x": -282,
    "y": -497
  },
  "groupLayout": {
    "_class": "MSImmutableFreeformGroupLayout"
  },
  "hasBackgroundColor": true,
  "hasClickThrough": true,
  "hasClippingMask": false,
  "horizontalRulerData": {
    "_class": "rulerData",
    "base": 0,
    "guides": [
    ]
  },
  "includeBackgroundColorInExport": false,
  "includeBackgroundColorInInstance": false,
  "includeInCloudUpload": true,
  "isFixedToViewport": false,
  "isFlippedHorizontal": false,
  "isFlippedVertical": false,
  "isFlowHome": false,
  "isLocked": false,
  "isVisible": true,
  "layerListExpandedType": 2,
  "layers": [
    {
      "class": "rectangle",
      "id": "FCE482CB-DC38-4835-BAD3-DA62FCAAFE41"
    },
    {
      "class": "rectangle",
      "id": "FA6FBECC-37D5-44A3-8873-17C45045618E"
    },
    {
      "class": "group",
      "id": "E3F39977-1C1A-465B-9431-2D210EB91CE6"
    },
    {
      "class": "rectangle",
      "id": "7FAF6218-A4BC-495E-9CE8-A9570E14C1BF"
    }
  ],
  "name": "Clipboard illustration",
  "nameIsFixed": true,
  "overrideProperties": [
  ],
  "resizesContent": true,
  "resizingConstraint": 63,
  "resizingType": 0,
  "rotation": 0,
  "shouldBreakMaskChain": true,
  "style": {
    "_class": "style",
    "endMarkerType": 0,
    "miterLimit": 10,
    "startMarkerType": 0,
    "windingRule": 1
  },
  "symbolID": "37059CBF-8573-4E15-AF18-90F62DABB77D",
  "verticalRulerData": {
    "_class": "rulerData",
    "base": 0,
    "guides": [
    ]
  }
}