{
  "_class": "bitmap",
  "booleanOperation": -1,
  "clippingMask": "{{0, 0}, {1, 1}}",
  "clippingMaskMode": 0,
  "do_objectID": "393A68D1-BDB8-4A11-B0B4-A5F7579514B5",
  "exportOptions": {
    "_class": "exportOptions",
    "do_objectID": "0BAD4A74-BCF0-41A7-BF25-D0D573EEE33F",
    "exportFormats": [
    ],
    "includedLayerIds": [
    ],
    "layerOptions": 0,
    "shouldTrim": false
  },
  "fillReplacesImage": false,
  "frame": {
    "_class": "rect",
    "constrainProportions": false,
    "do_objectID": "C58B701A-E869-406F-8CDA-E067FA6A74C4",
    "height": 127,
    "width": 146.6375545851528,
    "x": 41.17903930131004,
    "y": 0
  },
  "hasClippingMask": false,
  "image": {
    "_class": "MSJSONFileReference",
    "_ref": "images/ad0a0137ff68e07803cf0fb07465a4bbaf4ae3e3.png",
    "_ref_class": "MSImageData"
  },
  "intendedDPI": 72,
  "isFixedToViewport": false,
  "isFlippedHorizontal": false,
  "isFlippedVertical": false,
  "isLocked": false,
  "isVisible": false,
  "layerListExpandedType": 0,
  "name": "box",
  "nameIsFixed": false,
  "resizingConstraint": 63,
  "resizingType": 0,
  "rotation": 0,
  "shouldBreakMaskChain": false,
  "style": {
    "_class": "style",
    "colorControls": {
      "_class": "colorControls",
      "brightness": 0,
      "contrast": 1.146963443396226,
      "do_objectID": "95B69E04-7C9A-4EA8-8C51-6B2B536772A5",
      "hue": 0,
      "isEnabled": true,
      "saturation": 0.2
    },
    "contextSettings": {
      "_class": "graphicsContextSettings",
      "blendMode": 0,
      "do_objectID": "8445159A-5FA0-4E89-B31D-CE9E0FFA6131",
      "opacity": 0.3020135788690476
    },
    "do_objectID": "22980DC1-C9CC-4CE7-89D2-6566D89FDE99",
    "endMarkerType": 0,
    "miterLimit": 10,
    "startMarkerType": 0,
    "windingRule": 1
  }
}